[
  {
    "id": "644b3b81-457b-490f-a00b-19a038b6de08",
    "data": [
      {
        "text": "whatever",
        "userDefined": false
      }
    ],
    "isTemplate": false,
    "count": 0,
    "updated": 0
  },
  {
    "id": "c78dbf97-366c-4267-af6d-959a1f743e50",
    "data": [
      {
        "text": "I ",
        "userDefined": false
      },
      {
        "text": "don",
        "meta": "@sys.ignore",
        "userDefined": false
      },
      {
        "text": "\u0027t care at ",
        "userDefined": false
      },
      {
        "text": "all",
        "meta": "@sys.ignore",
        "userDefined": false
      }
    ],
    "isTemplate": false,
    "count": 0,
    "updated": 0
  },
  {
    "id": "a0fe0cfe-a20c-43bb-880b-a2ac371809f8",
    "data": [
      {
        "text": "I ",
        "userDefined": false
      },
      {
        "text": "don\u0027t",
        "meta": "@sys.ignore",
        "userDefined": false
      },
      {
        "text": " care",
        "userDefined": false
      }
    ],
    "isTemplate": false,
    "count": 0,
    "updated": 0
  },
  {
    "id": "9927979f-124d-4da9-8086-d7e1e025a018",
    "data": [
      {
        "text": "not care at ",
        "userDefined": false
      },
      {
        "text": "all",
        "meta": "@sys.ignore",
        "userDefined": false
      }
    ],
    "isTemplate": false,
    "count": 0,
    "updated": 0
  },
  {
    "id": "e9c88a46-e714-4767-9164-b948779de533",
    "data": [
      {
        "text": "I do not care",
        "userDefined": false
      }
    ],
    "isTemplate": false,
    "count": 0,
    "updated": 0
  },
  {
    "id": "f5c69c14-0a9a-4cc0-af3b-bc7f93313c8e",
    "data": [
      {
        "text": "don",
        "meta": "@sys.ignore",
        "userDefined": false
      },
      {
        "text": "\u0027t care at ",
        "userDefined": false
      },
      {
        "text": "all",
        "meta": "@sys.ignore",
        "userDefined": false
      }
    ],
    "isTemplate": false,
    "count": 0,
    "updated": 0
  },
  {
    "id": "bdbeec26-ccf2-4064-b55a-3c515a79d93c",
    "data": [
      {
        "text": "not caring at ",
        "userDefined": false
      },
      {
        "text": "all",
        "meta": "@sys.ignore",
        "userDefined": false
      }
    ],
    "isTemplate": false,
    "count": 0,
    "updated": 0
  },
  {
    "id": "b85bddde-f001-4806-aa78-e56f709c21ed",
    "data": [
      {
        "text": "not caring",
        "userDefined": false
      }
    ],
    "isTemplate": false,
    "count": 0,
    "updated": 0
  },
  {
    "id": "5e6f9b7b-e161-4db2-be3e-b9f84e596c49",
    "data": [
      {
        "text": "I shouldn\u0027t care about this",
        "userDefined": false
      }
    ],
    "isTemplate": false,
    "count": 0,
    "updated": 0
  }
]