[
  {
    "id": "a3aae8cc-88fd-4d61-b17d-1440ed54e128",
    "data": [
      {
        "text": "what exactly do you mean",
        "userDefined": false
      }
    ],
    "isTemplate": false,
    "count": 1,
    "updated": 0
  },
  {
    "id": "b424c300-0a01-4204-886c-c01039a8a195",
    "data": [
      {
        "text": "what do you mean exactly",
        "userDefined": false
      }
    ],
    "isTemplate": false,
    "count": 0,
    "updated": 0
  },
  {
    "id": "f4b56bfc-f595-4811-ba65-2e4cf5e1c561",
    "data": [
      {
        "text": "is that what you mean",
        "userDefined": false
      }
    ],
    "isTemplate": false,
    "count": 0,
    "updated": 0
  },
  {
    "id": "2da6c6e6-be68-48b7-b418-566a8ed00ae6",
    "data": [
      {
        "text": "but what do you mean",
        "userDefined": false
      }
    ],
    "isTemplate": false,
    "count": 0,
    "updated": 0
  },
  {
    "id": "ff966691-72ec-4232-b6b9-0918a458f11a",
    "data": [
      {
        "text": "what do you mean",
        "userDefined": false
      }
    ],
    "isTemplate": false,
    "count": 0,
    "updated": 0
  }
]