[
  {
    "id": "f284c1b4-65c7-4b10-a2f4-f3fc3c6193ee",
    "data": [
      {
        "text": "advise me",
        "userDefined": false
      }
    ],
    "isTemplate": false,
    "count": 0,
    "updated": 0
  },
  {
    "id": "42148313-9784-4e83-9c29-06c9fb5553d2",
    "data": [
      {
        "text": "any suggestions",
        "userDefined": false
      }
    ],
    "isTemplate": false,
    "count": 0,
    "updated": 0
  },
  {
    "id": "c60198b4-cea0-4851-84f0-583281ff5486",
    "data": [
      {
        "text": "can you give me advice",
        "userDefined": false
      }
    ],
    "isTemplate": false,
    "count": 0,
    "updated": 0
  },
  {
    "id": "5f4c9de0-c3bf-4bb5-8af4-489758fbc62d",
    "data": [
      {
        "text": "give me a wise advice",
        "userDefined": false
      }
    ],
    "isTemplate": false,
    "count": 0,
    "updated": 0
  },
  {
    "id": "64488b16-8ce1-4122-881d-d39730af47f8",
    "data": [
      {
        "text": "can you advise me",
        "userDefined": false
      }
    ],
    "isTemplate": false,
    "count": 0,
    "updated": 0
  },
  {
    "id": "e3593c1e-f727-4a67-9ba7-b5d7d4e20af5",
    "data": [
      {
        "text": "help me with advice",
        "userDefined": false
      }
    ],
    "isTemplate": false,
    "count": 0,
    "updated": 0
  },
  {
    "id": "4a0c3196-867c-415b-9ff8-714570299a24",
    "data": [
      {
        "text": "guide ",
        "userDefined": false
      },
      {
        "text": "me",
        "meta": "@sys.ignore",
        "userDefined": false
      }
    ],
    "isTemplate": false,
    "count": 0,
    "updated": 0
  },
  {
    "id": "6c9e784e-92f8-4584-ac7e-0ec30a7a37f5",
    "data": [
      {
        "text": "what should I do about it",
        "userDefined": false
      }
    ],
    "isTemplate": false,
    "count": 1,
    "updated": 0
  },
  {
    "id": "01b0c6dc-91b6-4608-a648-11af903c8b0d",
    "data": [
      {
        "text": "give me some good advice",
        "userDefined": false
      }
    ],
    "isTemplate": false,
    "count": 1,
    "updated": 0
  },
  {
    "id": "a9d0ad5b-d9e0-49ab-ae22-951e36af6d89",
    "data": [
      {
        "text": "what should I do",
        "userDefined": false
      }
    ],
    "isTemplate": false,
    "count": 1,
    "updated": 0
  },
  {
    "id": "96527ff0-88d1-46f5-bb48-dc5339267bb5",
    "data": [
      {
        "text": "do you have any advice for me",
        "userDefined": false
      }
    ],
    "isTemplate": false,
    "count": 0,
    "updated": 0
  },
  {
    "id": "08bd6bca-d919-4777-9901-48861c5138da",
    "data": [
      {
        "text": "I need an advice from you",
        "userDefined": false
      }
    ],
    "isTemplate": false,
    "count": 0,
    "updated": 0
  },
  {
    "id": "96733482-41fb-4205-ac7a-b87fad3c3d39",
    "data": [
      {
        "text": "can I ask for your advice",
        "userDefined": false
      }
    ],
    "isTemplate": false,
    "count": 0,
    "updated": 0
  },
  {
    "id": "3224b6c5-3004-4a38-9ff9-207c2e2d133b",
    "data": [
      {
        "text": "can you offer any advice",
        "userDefined": false
      }
    ],
    "isTemplate": false,
    "count": 0,
    "updated": 0
  },
  {
    "id": "5d3fdf86-5049-4d8e-8388-794a24f96c1a",
    "data": [
      {
        "text": "what do you suggest",
        "userDefined": false
      }
    ],
    "isTemplate": false,
    "count": 1,
    "updated": 0
  },
  {
    "id": "3051f97f-9516-4a4e-9e1d-c0bde6e7037c",
    "data": [
      {
        "text": "I could use some advice",
        "userDefined": false
      }
    ],
    "isTemplate": false,
    "count": 0,
    "updated": 0
  },
  {
    "id": "63a16909-001f-4074-8349-f160a3282ca6",
    "data": [
      {
        "text": "any",
        "meta": "@sys.ignore",
        "userDefined": false
      },
      {
        "text": " advice",
        "userDefined": false
      }
    ],
    "isTemplate": false,
    "count": 0,
    "updated": 0
  },
  {
    "id": "b1a947bd-dd20-4417-ab6f-3b393831650f",
    "data": [
      {
        "text": "what can you recommend",
        "userDefined": false
      }
    ],
    "isTemplate": false,
    "count": 1,
    "updated": 0
  },
  {
    "id": "6d69f370-e290-47d9-a023-081f8d72be6a",
    "data": [
      {
        "text": "what do you recommend",
        "userDefined": false
      }
    ],
    "isTemplate": false,
    "count": 0,
    "updated": 0
  },
  {
    "id": "43cab6bd-6b1e-4857-9a09-a833dd210222",
    "data": [
      {
        "text": "I need advice",
        "userDefined": false
      }
    ],
    "isTemplate": false,
    "count": 0,
    "updated": 0
  },
  {
    "id": "73ec962a-a4a9-45da-8ddf-2a4b595ccb08",
    "data": [
      {
        "text": "I seek your advice",
        "userDefined": false
      }
    ],
    "isTemplate": false,
    "count": 0,
    "updated": 0
  },
  {
    "id": "6294e783-d71c-4152-868b-40c62a450aa0",
    "data": [
      {
        "text": "give me some advice about",
        "userDefined": false
      }
    ],
    "isTemplate": false,
    "count": 0,
    "updated": 0
  },
  {
    "id": "b432408c-e852-4af8-9726-6564fc083683",
    "data": [
      {
        "text": "what is your advice",
        "userDefined": false
      }
    ],
    "isTemplate": false,
    "count": 1,
    "updated": 0
  }
]